{
    "status": "1",
    "flag": "1",
    "data": {
        "age": "42年",
        "layout2": "2房2廳1衛",
        "layout": "2房2廳1衛",
        "listLayout": "2房2廳",
        "floor": "3F/6F",
        "shape": "電梯大樓",
        "parking": "無",
        "community": "",
        "cases_id": "0",
        "managefee": "",
        "traffic": "",
        "living": "近便利商店；傳統市場；百貨公司；公園綠地；學校；醫療機構；夜市",
        "area_intro": "主建物10.69坪，共用部分2.94坪，土地2.68坪",
        "area_intro_arr": [
            {
                "name": "土地坪數",
                "value": "2.68坪"
            },
            {
                "name": "登記總面積",
                "value": "13.63坪"
            },
            {
                "name": "主建物",
                "value": "10.69坪"
            },
            {
                "name": "共有部分",
                "value": "2.94坪"
            },
            {
                "name": "附屬建物",
                "value": "-"
            },
            {
                "name": "車位面積",
                "value": "-"
            }
        ],
        "title": "【百家-專業首選】【捷運善導寺商務套房】",
        "price": "771萬元",
        "price_value": "771",
        "kind": "住宅",
        "area": "13.63坪",
        "area_value": "13.63",
        "region": "台北市",
        "region_id": "1",
        "section": "中正區",
        "section_id": "1",
        "street": "林森北路",
        "addr": "5巷",
        "linkman": "【專營-雙北-桃園】",
        "identity": "仲介",
        "mobile": "0901-038-371",
        "telephone": "02-89135670",
        "email": "lazxwe@gmail.com",
        "unitprice": "56.57萬/坪",
        "posttime": "1621673684",
        "purpose_midify": "0",
        "mobile_header": "0901-038-371",
        "parking_new": "無",
        "is_hide_tel": "0",
        "tel_agreement": "0",
        "isrecmoney": "收取服務費",
        "warnmsg": "0",
        "is_recmoney": "1",
        "streetid": "25796",
        "alley": "5",
        "lane": "x",
        "addr_number": "x",
        "hide_addr_detail": "1",
        "edit_lane": "",
        "edit_addr_number": "11",
        "room": "2",
        "hall": "2",
        "toilet": "1",
        "balcony": "0",
        "is_balcony": "0",
        "floor_in_floor": "",
        "spacematerial_str": "",
        "spacematerial": "0",
        "carttype": "2",
        "shape_id": "2",
        "kind_id": "9",
        "housetype": "3",
        "pet": "",
        "cook": "",
        "edit_mobile": "0901-038-371",
        "edit_telephone": "02-89135670",
        "parking_shape": "電梯大樓",
        "parking_kind": "無",
        "manageprice": "0",
        "lift": "0",
        "area_unit": "1",
        "mainarea": "10.69坪",
        "modify_limit": "1",
        "community_id": "",
        "casesID": "1447112",
        "casesname": "【薪水成家】-【二成自備】-【八成貸款】",
        "json_no_hometools": {},
        "json_hometools": [
            {
                "name": "桌子",
                "value": "1",
                "status": "0"
            },
            {
                "name": "椅子",
                "value": "3",
                "status": "0"
            },
            {
                "name": "衣櫃",
                "value": "4",
                "status": "0"
            },
            {
                "name": "床",
                "value": "5",
                "status": "0"
            },
            {
                "name": "沙發",
                "value": "7",
                "status": "0"
            }
        ],
        "json_fixture": [
            {
                "name": "熱水器",
                "value": "1",
                "status": "0"
            },
            {
                "name": "天然瓦斯",
                "value": "2",
                "status": "0"
            },
            {
                "name": "電視",
                "value": "4",
                "status": "0"
            },
            {
                "name": "冰箱",
                "value": "5",
                "status": "0"
            },
            {
                "name": "冷氣",
                "value": "6",
                "status": "0"
            },
            {
                "name": "洗衣機",
                "value": "7",
                "status": "0"
            },
            {
                "name": "網路",
                "value": "14",
                "status": "0"
            },
            {
                "name": "第四台",
                "value": "15",
                "status": "0"
            },
            {
                "name": "養寵物",
                "value": "",
                "status": "0"
            },
            {
                "name": "開伙",
                "value": "",
                "status": "0"
            },
            {
                "name": "車位",
                "value": "",
                "status": "0"
            }
        ],
        "purpose": "住家用",
        "houseage": "42",
        "isrenting": "0",
        "isrent_ing": "否",
        "carport": "2",
        "hasCarport": "2",
        "cartplacetypeNew": "",
        "market": {
            "status": "1",
            "data": {
                "community": {
                    "name": "",
                    "id": ""
                },
                "bar": {
                    "show": "1",
                    "type": "1",
                    "params": {
                        "id": "1807717",
                        "build_type": "2"
                    },
                    "context": "林森北路5巷 · 查詢"
                }
            }
        },
        "livingID": "2,3,1,5,6,7,4",
        "fitment": "簡易裝潢",
        "fitmentID": "2",
        "id": "S9424153",
        "type": "sale",
        "remark": "http://www.104home.com.tw/images/index0_5.png Q1.什麼是法拍屋?http://www.104home.com.tw/classinfo/00.png 法拍屋就是遭到法院拍賣的房屋，被拍賣原因通常是欠債、欠稅、幫人作保...等， 簡單舉幾個法拍屋形成原因 :1.欠稅 : 包含營業稅、營產稅、個人所得稅...等及其他稅金，房屋拍賣所得會用來清償欠稅。2.為人作保 : 因為擔任他人的【連帶保證人】，結果原本的債務人跑路，自己得負責債務人債務，使原本屬於自己的房屋被查封拍賣。3.民事判決:經民事庭判定需要負賠償責任時，對方可持民事判決確定書申請假扣押進行查封不動產+動產。4.本票裁定 : 跟第三人、銀行、錢莊..等訂立借錢約定，如果未於期限內還款，經法院裁定後對方可申請假扣押進行查封不動產+動產。5.貸款沒繳 : 銀行催收達3個月仍不繳房貸，經法院公告且公文公示送達。6.信用卡費未繳 : 若銀行有執行名義（判決、支付命令、法院裁定...），即有權聲請法院強制執行有關債務人的不動產。 Q2.不點交和點交法拍屋有什麼不一樣?http://www.104home.com.tw/classinfo/00.png 【點交】在物件拍定後，繳清物件款項，取得權利移轉證書，即可向法院聲請點交，法院會安排時間履勘或強制執行現場點交，通常點交物件拍賣價格會比不點交物件貴。【不點交】在物件拍定後，繳清物件款項，取得權利移轉證書，但因物件拍賣前就已公告為不點交，法院不會安排進行點交，得標者必須自行與房屋內的佔用人協商，需要花多一點心力與時間才能完整取得房屋使用權。許多法拍新手不敢接觸不點交物件，但其實不點交拍賣價格會比點交物件便宜，反而有機會獲得較高利潤 ! Q3.買法拍屋會需要那些費用成本?http://www.104home.com.tw/classinfo/00.png 買法拍屋不是準備總底價的錢就好，也有其他相關費用，必須把這些都算在法拍屋成本裡，下面列出法拍屋常見費用。必須支出的費用 :1.投標金額 : 得標的價錢，在投標前須準備公告底價2成費用作為保證金，得標後7日內(含假日)將餘額繳清。2.稅費 : 買法拍屋要繳納的契稅。3.地政規費 : 如投標前申請謄本、得標後辦理過戶的地政規費。4.其他雜費 : 如房屋修繕費、搬家費、管理費、水電瓦斯費。可能支出的費用 :1.利息 : 如果透過貸款付費，在把法拍屋轉售賣掉前須負擔利息。2.代書費 : 如果委託代書辦理過戶、申報稅費就會有代書費。(向銀行代墊尾款須由銀行指定代書)。3.搬遷費 : 如果法拍屋遭人占用或出租，可能要付出一筆搬家費讓對方搬走。4.仲介費 : 委託代標公司投標的佣金費用。 Q4.為什麼我需要找法拍屋代標公司?http://www.104home.com.tw/classinfo/00.png 不管是法拍新手，或是事業忙碌又想利用法拍屋投資理財的人，透過專業可信賴的代標公司代為投標，絕對能節省時間、避免處理瑣碎繁雜的事宜，例如 : 房屋現況調查、是否有佔用情況/凶宅/海砂屋/輻射屋、產權是否完整、划算的投標價格計算、與現住人溝通協商...等，法拍屋代標機構都會協助客戶全程辦理、提供專業建議，讓客戶買的划算又安心 Q5.買法拍屋有哪些注意事項?http://www.104home.com.tw/classinfo/00.png 1.衡量自身財力 : 買法拍屋最重要的就是衡量自己的資金取得與週轉狀況，因為得標後7天內必須繳清剩餘款項，這段期間也有一些利息上的負擔。2.點交問題 : 確認想標購的法拍屋是點交或不點交物件。3.租賃權問題 : 確認物件是否正在出租，如果法院沒有排除租賃關係，標到後才發現裡面人有第三人租賃中，得標人必須繼續租賃契約直到期滿，或是另與租客協商(可能要幫對方出搬遷費)。另外還有一種狀況是原屋主可能事先造假租賃契約，造成標到後仍有合法佔用的問題。4.抵押權問題 : 確認拍定後抵押權是否塗銷，否則容易造成日後產權糾紛。5.產權移轉限制問題 : 確認物件是否有產權移轉的限制。6.優先購買權問題 : 確認物件是否有第三者擁有優先購買權(地上權、承租人、物件為農地...)否則一旦有這些情形又有優先購屋權人，就算標到了也可能無效。 Q6.哪裡可以得知法拍屋相關訊息http://www.104home.com.tw/classinfo/00.png 1.法院公告 : 地方法院會張貼法拍屋公告在布告欄，也可直接至司法院法拍屋查詢系統搜尋http://aomp.judicial.gov.tw/abbs/wkw/WHD2A00.jsp。2.銀行公告 : 當債權人為銀行時，此種物件稱為銀拍屋，銀行會將拍賣物件公告於官網上的法拍屋公告區。3.台灣金融資產服務股份有限公司 : 由法院委託民間公正第三人代辦拍賣的法拍屋，此種物件又稱為金拍屋http://www.tfasc.com.tw/。4.報紙廣告 : 有時報紙分類廣告也會提供法院拍賣物件資料，以中央日報最多。5.法拍屋代標業者官網 : 網路上有不少法拍屋代標網站，通常物件都經過整理歸納，非常方便一般民眾瀏覽。",
        "thumb": "https://hp2.591.com.tw/house/active/2021/05/22/162167361226620609_190x150.jpg",
        "photo": "https://hp2.591.com.tw/house/active/2021/05/22/162167361226620609_800x600x1559040.crop.water3.jpg|*|https://hp2.591.com.tw/house/active/2021/05/22/162167360379273400_800x600x1559040.crop.water3.jpg|*|https://hp2.591.com.tw/house/active/2021/05/22/162167360426434501_800x600x1559040.crop.water3.jpg|*|https://hp2.591.com.tw/house/active/2021/05/22/162167360380502205_800x600x1559040.crop.water3.jpg|*|https://hp2.591.com.tw/house/active/2021/05/22/162167360456291005_800x600x1559040.crop.water3.jpg|*|https://hp2.591.com.tw/house/active/2021/05/22/162167360493625302_800x600x1559040.crop.water3.jpg|*|https://hp2.591.com.tw/house/active/2021/05/22/162167360454940109_800x600x1559040.crop.water3.jpg|*|https://hp2.591.com.tw/house/active/2021/05/22/162167360693595902_800x600x1559040.crop.water3.jpg|*|https://hp2.591.com.tw/house/active/2021/05/22/162167360797677001_800x600x1559040.crop.water3.jpg|*|https://hp2.591.com.tw/house/active/2021/05/22/162167360816583602_800x600x1559040.crop.water3.jpg|*|https://hp2.591.com.tw/house/active/2021/05/22/162167360840561202_800x600x1559040.crop.water3.jpg|*|https://hp2.591.com.tw/house/active/2021/05/22/162167360875266706_800x600x1559040.crop.water3.jpg|*|https://hp2.591.com.tw/house/active/2021/05/22/162167360904825908_800x600x1559040.crop.water3.jpg|*|https://hp2.591.com.tw/house/active/2021/05/22/162167361138915104_800x600x1559040.crop.water3.jpg|*|https://hp2.591.com.tw/house/active/2021/05/22/162167361266781500_800x600x1559040.crop.water3.jpg|*|https://hp1.591.com.tw/house/map/887a0a53995ef379103aae1422bd13a5.png",
        "maxphoto": "https://hp2.591.com.tw/house/active/2021/05/22/162167361226620609_600x600x1559040.scale.jpg|*|https://hp2.591.com.tw/house/active/2021/05/22/162167360379273400_600x600x1559040.scale.jpg|*|https://hp2.591.com.tw/house/active/2021/05/22/162167360426434501_600x600x1559040.scale.jpg|*|https://hp2.591.com.tw/house/active/2021/05/22/162167360380502205_600x600x1559040.scale.jpg|*|https://hp2.591.com.tw/house/active/2021/05/22/162167360456291005_600x600x1559040.scale.jpg|*|https://hp2.591.com.tw/house/active/2021/05/22/162167360493625302_600x600x1559040.scale.jpg|*|https://hp2.591.com.tw/house/active/2021/05/22/162167360454940109_600x600x1559040.scale.jpg|*|https://hp2.591.com.tw/house/active/2021/05/22/162167360693595902_600x600x1559040.scale.jpg|*|https://hp2.591.com.tw/house/active/2021/05/22/162167360797677001_600x600x1559040.scale.jpg|*|https://hp2.591.com.tw/house/active/2021/05/22/162167360816583602_600x600x1559040.scale.jpg|*|https://hp2.591.com.tw/house/active/2021/05/22/162167360840561202_600x600x1559040.scale.jpg|*|https://hp2.591.com.tw/house/active/2021/05/22/162167360875266706_600x600x1559040.scale.jpg|*|https://hp2.591.com.tw/house/active/2021/05/22/162167360904825908_600x600x1559040.scale.jpg|*|https://hp2.591.com.tw/house/active/2021/05/22/162167361138915104_600x600x1559040.scale.jpg|*|https://hp2.591.com.tw/house/active/2021/05/22/162167361266781500_600x600x1559040.scale.jpg|*|https://hp1.591.com.tw/house/map/0c58f645541ce3dac31849729fe69b74.png",
        "photoalt": "|*||*||*||*||*||*||*||*||*||*||*||*||*||*||*|",
        "photoinfo": [
            {
                "photoid": "210303760",
                "photo": "https://hp2.591.com.tw/house/active/2021/05/22/162167361226620609_800x600x1559040.crop.water3.jpg",
                "maxphoto": "https://hp2.591.com.tw/house/active/2021/05/22/162167361226620609_600x600x1559040.scale.jpg",
                "photoalt": "",
                "is_full": "0",
                "arround_url": "",
                "video": ""
            },
            {
                "photoid": "210303734",
                "photo": "https://hp2.591.com.tw/house/active/2021/05/22/162167360379273400_800x600x1559040.crop.water3.jpg",
                "maxphoto": "https://hp2.591.com.tw/house/active/2021/05/22/162167360379273400_600x600x1559040.scale.jpg",
                "photoalt": "",
                "is_full": "0",
                "arround_url": "",
                "video": ""
            },
            {
                "photoid": "210303737",
                "photo": "https://hp2.591.com.tw/house/active/2021/05/22/162167360426434501_800x600x1559040.crop.water3.jpg",
                "maxphoto": "https://hp2.591.com.tw/house/active/2021/05/22/162167360426434501_600x600x1559040.scale.jpg",
                "photoalt": "",
                "is_full": "0",
                "arround_url": "",
                "video": ""
            },
            {
                "photoid": "210303735",
                "photo": "https://hp2.591.com.tw/house/active/2021/05/22/162167360380502205_800x600x1559040.crop.water3.jpg",
                "maxphoto": "https://hp2.591.com.tw/house/active/2021/05/22/162167360380502205_600x600x1559040.scale.jpg",
                "photoalt": "",
                "is_full": "0",
                "arround_url": "",
                "video": ""
            },
            {
                "photoid": "210303739",
                "photo": "https://hp2.591.com.tw/house/active/2021/05/22/162167360456291005_800x600x1559040.crop.water3.jpg",
                "maxphoto": "https://hp2.591.com.tw/house/active/2021/05/22/162167360456291005_600x600x1559040.scale.jpg",
                "photoalt": "",
                "is_full": "0",
                "arround_url": "",
                "video": ""
            },
            {
                "photoid": "210303740",
                "photo": "https://hp2.591.com.tw/house/active/2021/05/22/162167360493625302_800x600x1559040.crop.water3.jpg",
                "maxphoto": "https://hp2.591.com.tw/house/active/2021/05/22/162167360493625302_600x600x1559040.scale.jpg",
                "photoalt": "",
                "is_full": "0",
                "arround_url": "",
                "video": ""
            },
            {
                "photoid": "210303738",
                "photo": "https://hp2.591.com.tw/house/active/2021/05/22/162167360454940109_800x600x1559040.crop.water3.jpg",
                "maxphoto": "https://hp2.591.com.tw/house/active/2021/05/22/162167360454940109_600x600x1559040.scale.jpg",
                "photoalt": "",
                "is_full": "0",
                "arround_url": "",
                "video": ""
            },
            {
                "photoid": "210303748",
                "photo": "https://hp2.591.com.tw/house/active/2021/05/22/162167360693595902_800x600x1559040.crop.water3.jpg",
                "maxphoto": "https://hp2.591.com.tw/house/active/2021/05/22/162167360693595902_600x600x1559040.scale.jpg",
                "photoalt": "",
                "is_full": "0",
                "arround_url": "",
                "video": ""
            },
            {
                "photoid": "210303750",
                "photo": "https://hp2.591.com.tw/house/active/2021/05/22/162167360797677001_800x600x1559040.crop.water3.jpg",
                "maxphoto": "https://hp2.591.com.tw/house/active/2021/05/22/162167360797677001_600x600x1559040.scale.jpg",
                "photoalt": "",
                "is_full": "0",
                "arround_url": "",
                "video": ""
            },
            {
                "photoid": "210303753",
                "photo": "https://hp2.591.com.tw/house/active/2021/05/22/162167360816583602_800x600x1559040.crop.water3.jpg",
                "maxphoto": "https://hp2.591.com.tw/house/active/2021/05/22/162167360816583602_600x600x1559040.scale.jpg",
                "photoalt": "",
                "is_full": "0",
                "arround_url": "",
                "video": ""
            },
            {
                "photoid": "210303754",
                "photo": "https://hp2.591.com.tw/house/active/2021/05/22/162167360840561202_800x600x1559040.crop.water3.jpg",
                "maxphoto": "https://hp2.591.com.tw/house/active/2021/05/22/162167360840561202_600x600x1559040.scale.jpg",
                "photoalt": "",
                "is_full": "0",
                "arround_url": "",
                "video": ""
            },
            {
                "photoid": "210303755",
                "photo": "https://hp2.591.com.tw/house/active/2021/05/22/162167360875266706_800x600x1559040.crop.water3.jpg",
                "maxphoto": "https://hp2.591.com.tw/house/active/2021/05/22/162167360875266706_600x600x1559040.scale.jpg",
                "photoalt": "",
                "is_full": "0",
                "arround_url": "",
                "video": ""
            },
            {
                "photoid": "210303756",
                "photo": "https://hp2.591.com.tw/house/active/2021/05/22/162167360904825908_800x600x1559040.crop.water3.jpg",
                "maxphoto": "https://hp2.591.com.tw/house/active/2021/05/22/162167360904825908_600x600x1559040.scale.jpg",
                "photoalt": "",
                "is_full": "0",
                "arround_url": "",
                "video": ""
            },
            {
                "photoid": "210303759",
                "photo": "https://hp2.591.com.tw/house/active/2021/05/22/162167361138915104_800x600x1559040.crop.water3.jpg",
                "maxphoto": "https://hp2.591.com.tw/house/active/2021/05/22/162167361138915104_600x600x1559040.scale.jpg",
                "photoalt": "",
                "is_full": "0",
                "arround_url": "",
                "video": ""
            },
            {
                "photoid": "210303761",
                "photo": "https://hp2.591.com.tw/house/active/2021/05/22/162167361266781500_800x600x1559040.crop.water3.jpg",
                "maxphoto": "https://hp2.591.com.tw/house/active/2021/05/22/162167361266781500_600x600x1559040.scale.jpg",
                "photoalt": "",
                "is_full": "0",
                "arround_url": "",
                "video": ""
            }
        ],
        "video_url": "",
        "move_house": "",
        "money_evaluate": "",
        "lat": "25.0462184",
        "lng": "121.5252802",
        "share1": "台北市中正區，住宅出售，2房2廳1衛，771萬元，詳情：",
        "share2": "https://www.591.com.tw/2S?salt=uv5A&s=t",
        "share3": "來自【591中古屋】",
        "mortgage_rate": "0.31",
        "mortgage_info": "首付約154萬，月還款17,950元",
        "plan_act_info": "",
        "plan_act_url": "",
        "info": [
            {
                "name": "單價",
                "value": "56.57萬/坪"
            },
            {
                "name": "現況",
                "value": "住宅"
            },
            {
                "name": "法定用途",
                "value": "住家用"
            },
            {
                "name": "樓層",
                "value": "3F/6F"
            },
            {
                "name": "裝潢",
                "value": "簡易裝潢"
            },
            {
                "name": "帶租約",
                "value": "否"
            },
            {
                "name": "屋齡",
                "value": "42年"
            },
            {
                "name": "型態",
                "value": "電梯大樓"
            }
        ],
        "showAd": "",
        "wechat_id": "1559040",
        "head_img": "",
        "im_uid": "",
        "im_name": "",
        "foot_news_list": [
            {
                "jump_id": "6701",
                "browse_num_txt": "1.4萬",
                "summary": "實登2.0終於7月上路，其中預售屋全面納管，包括契約備查、即時登錄，以往為人詬病有如「黑箱」作業的預售屋市場，是否有轉白的契機。",
                "type": "15",
                "first_tag": "政策解讀",
                "tag": "",
                "author_type": "0",
                "show_type": "1",
                "cover": [
                    "https://hp1.591.com.tw/house/active/2021/06/22/162432445089168806_240x170.crop.jpg"
                ],
                "praise_num_txt": "117",
                "title": "實登2.0｜預售屋即時登錄後 這點才是關鍵",
                "browse_num": "14354",
                "week_browse": "990",
                "share_num": "312",
                "jump_url": "https://m.591.com.tw/v2/news/6701",
                "praise_num": "117",
                "show_time": "1624600320",
                "type_name": "政策解讀",
                "time": "2021-06-25",
                "share_num_txt": "312"
            },
            {
                "jump_id": "6787",
                "praise_num_txt": "110",
                "cover": [
                    "https://hp1.591.com.tw/house/active/2021/07/13/162616411325764100_240x170.crop.jpg"
                ],
                "show_time": "1626165023",
                "share_num": "516",
                "type": "1",
                "first_tag": "統計資料",
                "week_browse": "17560",
                "browse_num_txt": "1.7萬",
                "type_name": "即時新聞",
                "jump_url": "https://m.591.com.tw/v2/news/6787",
                "praise_num": "110",
                "browse_num": "17880",
                "show_type": "1",
                "summary": "內政部日前發布最新「住宅需求動向調查」，發現受訪對象最常遭遇的租屋糾紛，包括租金任意調漲、申請補貼被刁難、修繕責任判定爭議、戶籍無法遷入。",
                "author_type": "0",
                "title": "房東任意漲租、刁難入籍 專家提解方",
                "time": "2021-07-13",
                "tag": "新聞",
                "share_num_txt": "516"
            },
            {
                "tag": "",
                "author_type": "0",
                "summary": "營建署表示，因應疫情，今年申請方式只開放線上及郵寄申請，不開放臨櫃受理。但為簡政便民，營建署提供「快速通關」服務。",
                "first_tag": "政策解讀",
                "browse_num_txt": "3.9萬",
                "show_time": "1625641740",
                "cover": [
                    "https://hp1.591.com.tw/house/active/2021/07/07/162564034113454202_240x170.crop.jpg"
                ],
                "show_type": "1",
                "week_browse": "8548",
                "jump_url": "https://m.591.com.tw/v2/news/6760",
                "type_name": "政策解讀",
                "share_num": "3058",
                "title": "租金補貼8/2開跑 原申請戶可「快速通關」",
                "type": "15",
                "share_num_txt": "3058",
                "praise_num_txt": "230",
                "browse_num": "39800",
                "time": "2021-07-07",
                "praise_num": "230",
                "jump_id": "6760"
            }
        ],
        "econ_name": "【百家亞太國際地產有限公司】",
        "is_service_fee": "1",
        "company_name": "【百家亞太國際地產有限公司】",
        "medium_face": "http://upload.591.com.tw/user/2019/06/18/156086338604261409.jpg",
        "approve_status": "pass",
        "line": "",
        "edit_status": "0",
        "old_kind": "0",
        "device": "touch",
        "is_business": "",
        "appVersionCode": "",
        "saletype": "0",
        "no_statis": "",
        "good_house_tags": {}
    },
    "meta": {
        "title": "【百家-專業首選】【捷運善導寺商務套房】-台北市房屋出售-591售屋網",
        "keywords": "【百家-專業首選】【捷運善導寺商務套房】,591售屋網,實價登錄",
        "description": "591售屋網為您提供台北市中古屋出售，台北市中正區5巷房屋出售，【百家-專業首選】【捷運善導寺商務套房】。買房子就上591售屋網！",
        "ogimage": "https://hp2.591.com.tw/house/active/2021/05/22/162167361226620609_750x666.jpg"
    },
    "bluekai_data": {
        "region_id": "1",
        "section_id": "1",
        "sale_price": "700-799",
        "rental_price": "",
        "unit_price_per_ping": "55-59.9",
        "room": "2",
        "shape": "2",
        "mrt_city": "",
        "mrt_line": "",
        "tag": "",
        "type": "sale",
        "kind": "9",
        "page": ""
    },
    "update": "2021-07-16 22:47:56",
    "is_login_time_out": "1"
}